[
  {
    "symbol": "PRK",
    "end_date": "2015-03-31",
    "amend": "False",
    "period_focus": "Q1",
    "fiscal_year": 2015,
    "doc_type": "10-Q",
    "revenues": 83891000,
    "op_income": "",
    "net_income": 19044000,
    "eps_basic": 1.24,
    "eps_diluted": 1.23,
    "dividend": 0.94,
    "assets": 7303999000,
    "cur_assets": "",
    "cur_liab": "",
    "cash": 108528000,
    "equity": 707431000,
    "cash_flow_op": 9076000,
    "cash_flow_inv": 53658000,
    "cash_flow_fin": 280052000
  },
  {
    "symbol": "ACW",
    "end_date": "2015-03-31",
    "amend": "False",
    "period_focus": "Q1",
    "fiscal_year": 2015,
    "doc_type": "10-Q",
    "revenues": 183659000,
    "op_income": 9328000,
    "net_income": -588000,
    "eps_basic": -0.01,
    "eps_diluted": -0.01,
    "dividend": 0,
    "assets": 598891000,
    "cur_assets": 155330000,
    "cur_liab": 94430000,
    "cash": 17570000,
    "equity": 31789000,
    "cash_flow_op": -10490000,
    "cash_flow_inv": -4071000,
    "cash_flow_fin": 2358000
  },
  {
    "symbol": "AXE",
    "end_date": "2015-04-03",
    "amend": "False",
    "period_focus": "Q1",
    "fiscal_year": 2015,
    "doc_type": "10-Q",
    "revenues": 1385100000,
    "op_income": 59300000,
    "net_income": 19100000,
    "eps_basic": 0.58,
    "eps_diluted": 0.57,
    "dividend": 0,
    "assets": 3509200000,
    "cur_assets": 2553600000,
    "cur_liab": 984000000,
    "cash": 101200000,
    "equity": 1114500000,
    "cash_flow_op": 18000000,
    "cash_flow_inv": -8600000,
    "cash_flow_fin": -6600000
  },
  {
    "symbol": "AVT",
    "end_date": "2015-03-28",
    "amend": "False",
    "period_focus": "Q3",
    "fiscal_year": 2015,
    "doc_type": "10-Q",
    "revenues": 6736860000,
    "op_income": 203712000,
    "net_income": 121529000,
    "eps_basic": 0.89,
    "eps_diluted": 0.88,
    "dividend": 0.16,
    "assets": 10614505000,
    "cur_assets": 8483957000,
    "cur_liab": 4240972000,
    "cash": 803468000,
    "equity": 4501510000,
    "cash_flow_op": 284552000,
    "cash_flow_inv": -142187000,
    "cash_flow_fin": -213573000
  },
  {
    "symbol": "BAS",
    "end_date": "2015-03-31",
    "amend": "False",
    "period_focus": "Q1",
    "fiscal_year": 2015,
    "doc_type": "10-Q",
    "revenues": 261721000,
    "op_income": -33769000,
    "net_income": -32624000,
    "eps_basic": -0.81,
    "eps_diluted": -0.81,
    "dividend": 0,
    "assets": 1499550000,
    "cur_assets": 346247000,
    "cur_liab": 150926000,
    "cash": 104936000,
    "equity": 307464000,
    "cash_flow_op": 65777000,
    "cash_flow_inv": -22600000,
    "cash_flow_fin": -18156000
  },
  {
    "symbol": "BBT",
    "end_date": "2015-03-31",
    "amend": "False",
    "period_focus": "Q1",
    "fiscal_year": 2015,
    "doc_type": "10-Q",
    "revenues": 2490000000,
    "op_income": "",
    "net_income": 488000000,
    "eps_basic": 0.68,
    "eps_diluted": 0.67,
    "dividend": 0.24,
    "assets": 189228000000,
    "cur_assets": "",
    "cur_liab": "",
    "cash": 1452000000,
    "equity": 24738000000,
    "cash_flow_op": -583000000,
    "cash_flow_inv": 783000000,
    "cash_flow_fin": -526000000
  },
  {
    "symbol": "BRX",
    "end_date": "2015-03-31",
    "amend": "False",
    "period_focus": "Q1",
    "fiscal_year": 2015,
    "doc_type": "10-Q",
    "revenues": 315293000,
    "op_income": "",
    "net_income": 30423000,
    "eps_basic": 0.1,
    "eps_diluted": 0.1,
    "dividend": 0.225,
    "assets": 9639179000,
    "cur_assets": "",
    "cur_liab": "",
    "cash": 68184000,
    "equity": 2952718000,
    "cash_flow_op": 112937000,
    "cash_flow_inv": -31872000,
    "cash_flow_fin": -73476000
  },
  {
    "symbol": "BDN",
    "end_date": "2015-03-31",
    "amend": "False",
    "period_focus": "Q1",
    "fiscal_year": 2015,
    "doc_type": "10-Q",
    "revenues": 150406000,
    "op_income": 29961000,
    "net_income": 6710000,
    "eps_basic": 0.04,
    "eps_diluted": 0.04,
    "dividend": 0.15,
    "assets": 4845656000,
    "cur_assets": "",
    "cur_liab": "",
    "cash": 309083000,
    "equity": 2138576000,
    "cash_flow_op": 45611000,
    "cash_flow_inv": 38311000,
    "cash_flow_fin": -32341000
  },
  {
    "symbol": "BMY",
    "end_date": "2015-03-31",
    "amend": "False",
    "period_focus": "Q1",
    "fiscal_year": 2015,
    "doc_type": "10-Q",
    "revenues": 4041000000,
    "op_income": "",
    "net_income": 1186000000,
    "eps_basic": 0.71,
    "eps_diluted": 0.71,
    "dividend": 0.37,
    "assets": 33579000000,
    "cur_assets": 14925000000,
    "cur_liab": 7689000000,
    "cash": 6294000000,
    "equity": 15689000000,
    "cash_flow_op": 626000000,
    "cash_flow_inv": 754000000,
    "cash_flow_fin": -682000000
  },
  {
    "symbol": "BCR",
    "end_date": "2015-03-31",
    "amend": "False",
    "period_focus": "Q1",
    "fiscal_year": 2015,
    "doc_type": "10-Q",
    "revenues": 819700000,
    "op_income": "",
    "net_income": 137700000,
    "eps_basic": 1.85,
    "eps_diluted": 1.82,
    "dividend": 0,
    "assets": 5056700000,
    "cur_assets": 2036800000,
    "cur_liab": 903000000,
    "cash": 1004200000,
    "equity": 1748800000,
    "cash_flow_op": 114000000,
    "cash_flow_inv": -3300000,
    "cash_flow_fin": -49100000
  },
  {
    "symbol": "COG",
    "end_date": "2015-03-31",
    "amend": "False",
    "period_focus": "Q1",
    "fiscal_year": 2015,
    "doc_type": "10-Q",
    "revenues": 464765000,
    "op_income": 87295000,
    "net_income": 40255000,
    "eps_basic": 0.1,
    "eps_diluted": 0.1,
    "dividend": 0.02,
    "assets": 5512323000,
    "cur_assets": 349403000,
    "cur_liab": 402746000,
    "cash": 13948000,
    "equity": 2175531000,
    "cash_flow_op": 267381000,
    "cash_flow_inv": -397239000,
    "cash_flow_fin": 122852000
  },
  {
    "symbol": "CAM",
    "end_date": "2015-03-31",
    "amend": "False",
    "period_focus": "Q1",
    "fiscal_year": 2015,
    "doc_type": "10-Q",
    "revenues": 2273000000,
    "op_income": "",
    "net_income": 49000000,
    "eps_basic": 0.25,
    "eps_diluted": 0.25,
    "dividend": 0,
    "assets": 11805000000,
    "cur_assets": 7251000000,
    "cur_liab": 3618000000,
    "cash": 1322000000,
    "equity": 5029000000,
    "cash_flow_op": -193000000,
    "cash_flow_inv": 437000000,
    "cash_flow_fin": -396000000
  },
  {
    "symbol": "KMX",
    "end_date": "2015-02-28",
    "amend": "False",
    "period_focus": "FY",
    "fiscal_year": 2015,
    "doc_type": "10-K",
    "revenues": 14268716000,
    "op_income": "",
    "net_income": 597358000,
    "eps_basic": 2.77,
    "eps_diluted": 2.73,
    "dividend": 0,
    "assets": 13198201000,
    "cur_assets": 2599038000,
    "cur_liab": 997173000,
    "cash": 27606000,
    "equity": 3156785000,
    "cash_flow_op": -968130000,
    "cash_flow_inv": -360744000,
    "cash_flow_fin": 728579000
  },
  {
    "symbol": "CNC",
    "end_date": "2015-03-31",
    "amend": "False",
    "period_focus": "Q1",
    "fiscal_year": 2015,
    "doc_type": "10-Q",
    "revenues": 5131000000,
    "op_income": 129000000,
    "net_income": 63000000,
    "eps_basic": 0.53,
    "eps_diluted": 0.51,
    "dividend": 0,
    "assets": 6696000000,
    "cur_assets": 3590000000,
    "cur_liab": 3343000000,
    "cash": 1666000000,
    "equity": 1837000000,
    "cash_flow_op": 45000000,
    "cash_flow_inv": -225000000,
    "cash_flow_fin": 236000000
  },
  {
    "symbol": "CBI",
    "end_date": "2015-03-31",
    "amend": "False",
    "period_focus": "Q1",
    "fiscal_year": 2015,
    "doc_type": "10-Q",
    "revenues": 3125745000,
    "op_income": 246798000,
    "net_income": 132228000,
    "eps_basic": 1.22,
    "eps_diluted": 1.21,
    "dividend": 0.07,
    "assets": 9718241000,
    "cur_assets": 3898210000,
    "cur_liab": 4587535000,
    "cash": 347017000,
    "equity": 2986006000,
    "cash_flow_op": -289871000,
    "cash_flow_inv": -56879000,
    "cash_flow_fin": 403409000
  },
  {
    "symbol": "COR",
    "end_date": "2015-03-31",
    "amend": "False",
    "period_focus": "Q1",
    "fiscal_year": 2015,
    "doc_type": "10-Q",
    "revenues": 74757000,
    "op_income": 13336000,
    "net_income": 4568000,
    "eps_basic": 0.21,
    "eps_diluted": 0.21,
    "dividend": 0,
    "assets": 1086287000,
    "cur_assets": "",
    "cur_liab": "",
    "cash": 12058000,
    "equity": 649597000,
    "cash_flow_op": 30748000,
    "cash_flow_inv": -23102000,
    "cash_flow_fin": -6250000
  },
  {
    "symbol": "CLGX",
    "end_date": "2015-03-31",
    "amend": "False",
    "period_focus": "Q1",
    "fiscal_year": 2015,
    "doc_type": "10-Q",
    "revenues": 364772000,
    "op_income": 49265000,
    "net_income": 29179000,
    "eps_basic": 0.33,
    "eps_diluted": 0.32,
    "dividend": 0,
    "assets": 3473975000,
    "cur_assets": 501580000,
    "cur_liab": 532059000,
    "cash": 89706000,
    "equity": 1028187000,
    "cash_flow_op": 40234000,
    "cash_flow_inv": -22883000,
    "cash_flow_fin": -31932000
  },
  {
    "symbol": "CYS",
    "end_date": "2015-03-31",
    "amend": "False",
    "period_focus": "Q1",
    "fiscal_year": 2015,
    "doc_type": "10-Q",
    "revenues": "",
    "op_income": "",
    "net_income": 49394000,
    "eps_basic": 0.31,
    "eps_diluted": 0.31,
    "dividend": 0.3,
    "assets": 15595021000,
    "cur_assets": "",
    "cur_liab": "",
    "cash": 7170000,
    "equity": 1940636000,
    "cash_flow_op": 53889000,
    "cash_flow_inv": 566265000,
    "cash_flow_fin": -617307000
  },
  {
    "symbol": "DHI",
    "end_date": "2015-03-31",
    "amend": "False",
    "period_focus": "Q2",
    "fiscal_year": 2015,
    "doc_type": "10-Q",
    "revenues": 2398000000,
    "op_income": "",
    "net_income": 147900000,
    "eps_basic": 0.4,
    "eps_diluted": 0.4,
    "dividend": 0.0625,
    "assets": 10713100000,
    "cur_assets": "",
    "cur_liab": "",
    "cash": 697700000,
    "equity": 5421000000,
    "cash_flow_op": -168800000,
    "cash_flow_inv": -29300000,
    "cash_flow_fin": 234000000
  },
  {
    "symbol": "ALXN",
    "end_date": "2015-03-31",
    "amend": "False",
    "period_focus": "Q1",
    "fiscal_year": 2015,
    "doc_type": "10-Q",
    "revenues": 600333000,
    "op_income": 103707000,
    "net_income": 91323000,
    "eps_basic": 0.46,
    "eps_diluted": 0.45,
    "dividend": 0,
    "assets": 4414925000,
    "cur_assets": 2852987000,
    "cur_liab": 580439000,
    "cash": 916814000,
    "equity": 3516902000,
    "cash_flow_op": 23034000,
    "cash_flow_inv": -48423000,
    "cash_flow_fin": 5074000
  },
  {
    "symbol": "DTE",
    "end_date": "2015-03-31",
    "amend": "False",
    "period_focus": "Q1",
    "fiscal_year": 2015,
    "doc_type": "10-Q",
    "revenues": 2984000000,
    "op_income": 461000000,
    "net_income": 273000000,
    "eps_basic": 1.53,
    "eps_diluted": 1.53,
    "dividend": 0.69,
    "assets": 28068000000,
    "cur_assets": 2788000000,
    "cur_liab": 1839000000,
    "cash": 99000000,
    "equity": 8678000000,
    "cash_flow_op": 747000000,
    "cash_flow_inv": -556000000,
    "cash_flow_fin": -140000000
  },
  {
    "symbol": "ALTR",
    "end_date": "2015-03-27",
    "amend": "False",
    "period_focus": "Q1",
    "fiscal_year": 2015,
    "doc_type": "10-Q",
    "revenues": 435485000,
    "op_income": "",
    "net_income": 94852000,
    "eps_basic": 0.31,
    "eps_diluted": 0.31,
    "dividend": 0.18,
    "assets": 5767065000,
    "cur_assets": 3154774000,
    "cur_liab": 637738000,
    "cash": 2207101000,
    "equity": 3302747000,
    "cash_flow_op": 136633000,
    "cash_flow_inv": -242848000,
    "cash_flow_fin": -113051000
  },
  {
    "symbol": "AMZN",
    "end_date": "2015-03-31",
    "amend": "False",
    "period_focus": "Q1",
    "fiscal_year": 2015,
    "doc_type": "10-Q",
    "revenues": 22717000000,
    "op_income": 255000000,
    "net_income": -57000000,
    "eps_basic": -0.12,
    "eps_diluted": -0.12,
    "dividend": 0,
    "assets": 50075000000,
    "cur_assets": 25922000000,
    "cur_liab": 23177000000,
    "cash": 10237000000,
    "equity": 10873000000,
    "cash_flow_op": -1499000000,
    "cash_flow_inv": -1847000000,
    "cash_flow_fin": -652000000
  },
  {
    "symbol": "AAL",
    "end_date": "2015-03-31",
    "amend": "False",
    "period_focus": "Q1",
    "fiscal_year": 2015,
    "doc_type": "10-Q",
    "revenues": 9827000000,
    "op_income": 1216000000,
    "net_income": 932000000,
    "eps_basic": 1.34,
    "eps_diluted": 1.3,
    "dividend": 0.1,
    "assets": 46754000000,
    "cur_assets": 14129000000,
    "cur_liab": 14233000000,
    "cash": 1048000000,
    "equity": 2764000000,
    "cash_flow_op": 2494000000,
    "cash_flow_inv": -3202000000,
    "cash_flow_fin": 762000000
  },
  {
    "symbol": "AMGN",
    "end_date": "2015-03-31",
    "amend": "False",
    "period_focus": "Q1",
    "fiscal_year": 2015,
    "doc_type": "10-Q",
    "revenues": 5033000000,
    "op_income": 2022000000,
    "net_income": 1623000000,
    "eps_basic": 2.13,
    "eps_diluted": 2.11,
    "dividend": 0.79,
    "assets": 68952000000,
    "cur_assets": 35064000000,
    "cur_liab": 6336000000,
    "cash": 2864000000,
    "equity": 26506000000,
    "cash_flow_op": 1329000000,
    "cash_flow_inv": -952000000,
    "cash_flow_fin": -1244000000
  },
  {
    "symbol": "ETH",
    "end_date": "2015-03-31",
    "amend": "False",
    "period_focus": "Q3",
    "fiscal_year": 2015,
    "doc_type": "10-Q",
    "revenues": 173259000,
    "op_income": 9226000,
    "net_income": 2536000,
    "eps_basic": 0.09,
    "eps_diluted": 0.09,
    "dividend": 0,
    "assets": 609038000,
    "cur_assets": 265343000,
    "cur_liab": 136553000,
    "cash": 58436000,
    "equity": 376123000,
    "cash_flow_op": 22451000,
    "cash_flow_inv": -723000,
    "cash_flow_fin": -71883000
  },
  {
    "symbol": "FII",
    "end_date": "2015-03-31",
    "amend": "False",
    "period_focus": "Q1",
    "fiscal_year": 2015,
    "doc_type": "10-Q",
    "revenues": 220522000,
    "op_income": 59038000,
    "net_income": 34829000,
    "eps_basic": 0.35,
    "eps_diluted": 0.35,
    "dividend": 0.25,
    "assets": 1119107000,
    "cur_assets": 322891000,
    "cur_liab": 114346000,
    "cash": 91833000,
    "equity": 620428000,
    "cash_flow_op": 14663000,
    "cash_flow_inv": -1951000,
    "cash_flow_fin": -36146000
  },
  {
    "symbol": "FICO",
    "end_date": "2015-03-31",
    "amend": "False",
    "period_focus": "Q2",
    "fiscal_year": 2015,
    "doc_type": "10-Q",
    "revenues": 207109000,
    "op_income": 34399000,
    "net_income": 18870000,
    "eps_basic": 0.6,
    "eps_diluted": 0.58,
    "dividend": 0,
    "assets": 1236651000,
    "cur_assets": 301755000,
    "cur_liab": 256083000,
    "cash": 86841000,
    "equity": 381162000,
    "cash_flow_op": 43282000,
    "cash_flow_inv": -66797000,
    "cash_flow_fin": 14504000
  },
  {
    "symbol": "AWRE",
    "end_date": "2015-03-31",
    "amend": "False",
    "period_focus": "Q1",
    "fiscal_year": 2015,
    "doc_type": "10-Q",
    "revenues": 4123000,
    "op_income": "",
    "net_income": 272000,
    "eps_basic": 0.01,
    "eps_diluted": 0.01,
    "dividend": 0,
    "assets": 56240000,
    "cur_assets": 49040000,
    "cur_liab": 2976000,
    "cash": 44685000,
    "equity": 53185000,
    "cash_flow_op": 10000,
    "cash_flow_inv": 195000,
    "cash_flow_fin": 495000
  },
  {
    "symbol": "BIIB",
    "end_date": "2015-03-31",
    "amend": "False",
    "period_focus": "Q1",
    "fiscal_year": 2015,
    "doc_type": "10-Q",
    "revenues": 2554963000,
    "op_income": 1117875000,
    "net_income": 822541000,
    "eps_basic": 3.5,
    "eps_diluted": 3.49,
    "dividend": 0,
    "assets": 15219454000,
    "cur_assets": 5258896000,
    "cur_liab": 1946231000,
    "cash": 1478051000,
    "equity": 11669458000,
    "cash_flow_op": 733037000,
    "cash_flow_inv": -502771000,
    "cash_flow_fin": 80756000
  },
  {
    "symbol": "FTI",
    "end_date": "2015-03-31",
    "amend": "False",
    "period_focus": "Q1",
    "fiscal_year": 2015,
    "doc_type": "10-Q",
    "revenues": -26400000,
    "op_income": 234500000,
    "net_income": 147600000,
    "eps_basic": 0.63,
    "eps_diluted": 0.63,
    "dividend": 0,
    "assets": 6971200000,
    "cur_assets": 4242500000,
    "cur_liab": 2504700000,
    "cash": 695100000,
    "equity": 2482000000,
    "cash_flow_op": 175600000,
    "cash_flow_inv": -81400000,
    "cash_flow_fin": -30900000
  },
  {
    "symbol": "FSL",
    "end_date": "2015-04-03",
    "amend": "False",
    "period_focus": "Q1",
    "fiscal_year": 2015,
    "doc_type": "10-Q",
    "revenues": 1169000000,
    "op_income": 179000000,
    "net_income": 70000000,
    "eps_basic": 0.23,
    "eps_diluted": 0.22,
    "dividend": 0,
    "assets": 3096000000,
    "cur_assets": 1983000000,
    "cur_liab": 809000000,
    "cash": 501000000,
    "equity": -3454000000,
    "cash_flow_op": 134000000,
    "cash_flow_inv": -75000000,
    "cash_flow_fin": -241000000
  },
  {
    "symbol": "CPLA",
    "end_date": "2015-03-31",
    "amend": "False",
    "period_focus": "Q1",
    "fiscal_year": 2015,
    "doc_type": "10-Q",
    "revenues": 109074000,
    "op_income": 16780000,
    "net_income": 10037000,
    "eps_basic": 0.82,
    "eps_diluted": 0.8,
    "dividend": 0.37,
    "assets": 258408000,
    "cur_assets": 160805000,
    "cur_liab": 48734000,
    "cash": 99423000,
    "equity": 198644000,
    "cash_flow_op": 19563000,
    "cash_flow_inv": -6815000,
    "cash_flow_fin": -7246000
  },
  {
    "symbol": "CDNS",
    "end_date": "2015-04-04",
    "amend": "False",
    "period_focus": "Q1",
    "fiscal_year": 2015,
    "doc_type": "10-Q",
    "revenues": 411366000,
    "op_income": 49285000,
    "net_income": 36259000,
    "eps_basic": 0.13,
    "eps_diluted": 0.12,
    "dividend": 0,
    "assets": 3062565000,
    "cur_assets": 1733644000,
    "cur_liab": 1226436000,
    "cash": 887736000,
    "equity": 1363190000,
    "cash_flow_op": 46688000,
    "cash_flow_inv": -8416000,
    "cash_flow_fin": -73682000
  },
  {
    "symbol": "HIG",
    "end_date": "2015-03-31",
    "amend": "False",
    "period_focus": "Q1",
    "fiscal_year": 2015,
    "doc_type": "10-Q",
    "revenues": 4617000000,
    "op_income": "",
    "net_income": 467000000,
    "eps_basic": 1.11,
    "eps_diluted": 1.08,
    "dividend": 0.18,
    "assets": 246960000000,
    "cur_assets": "",
    "cur_liab": "",
    "cash": 500000000,
    "equity": 19077000000,
    "cash_flow_op": 447000000,
    "cash_flow_inv": 295000000,
    "cash_flow_fin": -619000000
  },
  {
    "symbol": "HSP",
    "end_date": "2015-03-31",
    "amend": "False",
    "period_focus": "Q1",
    "fiscal_year": 2015,
    "doc_type": "10-Q",
    "revenues": 1174900000,
    "op_income": 133400000,
    "net_income": 75600000,
    "eps_basic": 0.44,
    "eps_diluted": 0.43,
    "dividend": 0,
    "assets": 6549600000,
    "cur_assets": 2788400000,
    "cur_liab": 1124300000,
    "cash": 643700000,
    "equity": 3436600000,
    "cash_flow_op": -100300000,
    "cash_flow_inv": -121800000,
    "cash_flow_fin": 75200000
  },
  {
    "symbol": "CHDN",
    "end_date": "2015-03-31",
    "amend": "False",
    "period_focus": "Q1",
    "fiscal_year": 2015,
    "doc_type": "10-Q",
    "revenues": 0,
    "op_income": -4128000,
    "net_income": -1558000,
    "eps_basic": -0.09,
    "eps_diluted": -0.09,
    "dividend": 0,
    "assets": 2302370000,
    "cur_assets": 202673000,
    "cur_liab": 341573000,
    "cash": 49525000,
    "equity": 698743000,
    "cash_flow_op": 89674000,
    "cash_flow_inv": -5084000,
    "cash_flow_fin": -101105000
  },
  {
    "symbol": "IPG",
    "end_date": "2015-03-31",
    "amend": "False",
    "period_focus": "Q1",
    "fiscal_year": 2015,
    "doc_type": "10-Q",
    "revenues": 1676000000,
    "op_income": 7800000,
    "net_income": -1800000,
    "eps_basic": 0,
    "eps_diluted": 0,
    "dividend": 0.12,
    "assets": 11200200000,
    "cur_assets": 6387500000,
    "cur_liab": 6224900000,
    "cash": 734300000,
    "equity": 1944700000,
    "cash_flow_op": -796900000,
    "cash_flow_inv": -20000000,
    "cash_flow_fin": -51100000
  },
  {
    "symbol": "COBZ",
    "end_date": "2015-03-31",
    "amend": "False",
    "period_focus": "Q1",
    "fiscal_year": 2015,
    "doc_type": "10-Q",
    "revenues": 37282000,
    "op_income": "",
    "net_income": 7189000,
    "eps_basic": 0.18,
    "eps_diluted": 0.18,
    "dividend": 0.04,
    "assets": 3090226000,
    "cur_assets": "",
    "cur_liab": "",
    "cash": 63336000,
    "equity": 315629000,
    "cash_flow_op": 2523000,
    "cash_flow_inv": -45620000,
    "cash_flow_fin": 22416000
  },
  {
    "symbol": "CPSS",
    "end_date": "2015-03-31",
    "amend": "False",
    "period_focus": "Q1",
    "fiscal_year": 2015,
    "doc_type": "10-Q",
    "revenues": 85989000,
    "op_income": "",
    "net_income": 8333000,
    "eps_basic": 0.33,
    "eps_diluted": 0.26,
    "dividend": 0,
    "assets": 1905453000,
    "cur_assets": "",
    "cur_liab": "",
    "cash": 20202000,
    "equity": 137018000,
    "cash_flow_op": 49816000,
    "cash_flow_inv": -108494000,
    "cash_flow_fin": 61021000
  },
  {
    "symbol": "CNMD",
    "end_date": "2015-03-31",
    "amend": "False",
    "period_focus": "Q1",
    "fiscal_year": 2015,
    "doc_type": "10-Q",
    "revenues": 177940000,
    "op_income": 10954000,
    "net_income": 6312000,
    "eps_basic": 0.23,
    "eps_diluted": 0.23,
    "dividend": 0.2,
    "assets": 1087746000,
    "cur_assets": 374066000,
    "cur_liab": 113485000,
    "cash": 65729000,
    "equity": 574090000,
    "cash_flow_op": 14809000,
    "cash_flow_inv": -4914000,
    "cash_flow_fin": -4634000
  },
  {
    "symbol": "KMI",
    "end_date": "2015-03-31",
    "amend": "False",
    "period_focus": "Q1",
    "fiscal_year": 2015,
    "doc_type": "10-Q",
    "revenues": 3597000000,
    "op_income": 1078000000,
    "net_income": 429000000,
    "eps_basic": 0.2,
    "eps_diluted": 0.2,
    "dividend": 0.48,
    "assets": 86164000000,
    "cur_assets": 3289000000,
    "cur_liab": 6784000000,
    "cash": 259000000,
    "equity": 35359000000,
    "cash_flow_op": 1256000000,
    "cash_flow_inv": -2775000000,
    "cash_flow_fin": 1468000000
  },
  {
    "symbol": "LAZ",
    "end_date": "2015-03-31",
    "amend": "False",
    "period_focus": "Q1",
    "fiscal_year": 2015,
    "doc_type": "10-Q",
    "revenues": 593885000,
    "op_income": 74663000,
    "net_income": 55953000,
    "eps_basic": 0.45,
    "eps_diluted": 0.42,
    "dividend": 1.3,
    "assets": 2827731000,
    "cur_assets": "",
    "cur_liab": "",
    "cash": 606336000,
    "equity": 537305000,
    "cash_flow_op": 34968000,
    "cash_flow_inv": -4011000,
    "cash_flow_fin": -454026000
  },
  {
    "symbol": "LEA",
    "end_date": "2015-03-28",
    "amend": "False",
    "period_focus": "Q1",
    "fiscal_year": 2015,
    "doc_type": "10-Q",
    "revenues": 4521400000,
    "op_income": "",
    "net_income": 147300000,
    "eps_basic": 1.88,
    "eps_diluted": 1.86,
    "dividend": 0.25,
    "assets": 9618400000,
    "cur_assets": 5642400000,
    "cur_liab": 4059900000,
    "cash": 748200000,
    "equity": 2891800000,
    "cash_flow_op": -66600000,
    "cash_flow_inv": -564200000,
    "cash_flow_fin": 314500000
  },
  {
    "symbol": "LYB",
    "end_date": "2015-03-31",
    "amend": "False",
    "period_focus": "Q1",
    "fiscal_year": 2015,
    "doc_type": "10-Q",
    "revenues": 8185000000,
    "op_income": 1575000000,
    "net_income": 1166000000,
    "eps_basic": 2.42,
    "eps_diluted": 2.41,
    "dividend": 0.7,
    "assets": 24006000000,
    "cur_assets": 11647000000,
    "cur_liab": 5060000000,
    "cash": 1616000000,
    "equity": 7506000000,
    "cash_flow_op": 1468000000,
    "cash_flow_inv": -443000000,
    "cash_flow_fin": -401000000
  },
  {
    "symbol": "MHO",
    "end_date": "2015-03-31",
    "amend": "False",
    "period_focus": "Q1",
    "fiscal_year": 2015,
    "doc_type": "10-Q",
    "revenues": 263159000,
    "op_income": 19956000,
    "net_income": 8349000,
    "eps_basic": 0.34,
    "eps_diluted": 0.31,
    "dividend": 0,
    "assets": 1250764000,
    "cur_assets": "",
    "cur_liab": "",
    "cash": 29958000,
    "equity": 553613000,
    "cash_flow_op": -29276000,
    "cash_flow_inv": -845000,
    "cash_flow_fin": 44544000
  },
  {
    "symbol": "MDP",
    "end_date": "2015-03-31",
    "amend": "False",
    "period_focus": "Q3",
    "fiscal_year": 2015,
    "doc_type": "10-Q",
    "revenues": 398179000,
    "op_income": 47106000,
    "net_income": 25256000,
    "eps_basic": 0.57,
    "eps_diluted": 0.56,
    "dividend": 0.4575,
    "assets": 2828723000,
    "cur_assets": 470327000,
    "cur_liab": 506703000,
    "cash": 19658000,
    "equity": 929737000,
    "cash_flow_op": 123295000,
    "cash_flow_inv": -191528000,
    "cash_flow_fin": 51304000
  },
  {
    "symbol": "MTX",
    "end_date": "2015-03-29",
    "amend": "False",
    "period_focus": "Q1",
    "fiscal_year": 2015,
    "doc_type": "10-Q",
    "revenues": 453300000,
    "op_income": 59900000,
    "net_income": 35100000,
    "eps_basic": 1.01,
    "eps_diluted": 1.01,
    "dividend": 0.05,
    "assets": 3159500000,
    "cur_assets": 869100000,
    "cur_liab": 314700000,
    "cash": 193900000,
    "equity": 899000000,
    "cash_flow_op": 19600000,
    "cash_flow_inv": -25900000,
    "cash_flow_fin": -38200000
  },
  {
    "symbol": "FALC",
    "end_date": "2015-03-31",
    "amend": "False",
    "period_focus": "Q1",
    "fiscal_year": 2015,
    "doc_type": "10-Q",
    "revenues": 19939876,
    "op_income": 6373960,
    "net_income": 4934176,
    "eps_basic": 0.12,
    "eps_diluted": 0.1,
    "dividend": 0,
    "assets": 38956754,
    "cur_assets": 29899325,
    "cur_liab": 27427908,
    "cash": 10090151,
    "equity": -5150844,
    "cash_flow_op": -267927,
    "cash_flow_inv": -269218,
    "cash_flow_fin": 31416
  },
  {
    "symbol": "NEM",
    "end_date": "2015-03-31",
    "amend": "False",
    "period_focus": "Q1",
    "fiscal_year": 2015,
    "doc_type": "10-Q",
    "revenues": 1972000000,
    "op_income": "",
    "net_income": 183000000,
    "eps_basic": 0.37,
    "eps_diluted": 0.37,
    "dividend": 0.025,
    "assets": 25602000000,
    "cur_assets": 6151000000,
    "cur_liab": 2834000000,
    "cash": 2598000000,
    "equity": 13363000000,
    "cash_flow_op": 625000000,
    "cash_flow_inv": -214000000,
    "cash_flow_fin": -196000000
  },
  {
    "symbol": "FWRD",
    "end_date": "2015-03-31",
    "amend": "False",
    "period_focus": "Q1",
    "fiscal_year": 2015,
    "doc_type": "10-Q",
    "revenues": 205918000,
    "op_income": 8249000,
    "net_income": 4837000,
    "eps_basic": 0.16,
    "eps_diluted": 0.16,
    "dividend": 0.12,
    "assets": 715387000,
    "cur_assets": 196735000,
    "cur_liab": 114013000,
    "cash": 54495000,
    "equity": 477014000,
    "cash_flow_op": 7459000,
    "cash_flow_inv": -67105000,
    "cash_flow_fin": 72712000
  },
  {
    "symbol": "P",
    "end_date": "2015-03-31",
    "amend": "False",
    "period_focus": "Q1",
    "fiscal_year": 2015,
    "doc_type": "10-Q",
    "revenues": 230764000,
    "op_income": -48395000,
    "net_income": -48257000,
    "eps_basic": -0.23,
    "eps_diluted": -0.23,
    "dividend": 0,
    "assets": 749870000,
    "cur_assets": 589491000,
    "cur_liab": 171950000,
    "cash": 221014000,
    "equity": 562674000,
    "cash_flow_op": 26982000,
    "cash_flow_inv": 16408000,
    "cash_flow_fin": 1825000
  },
  {
    "symbol": "HA",
    "end_date": "2015-03-31",
    "amend": "False",
    "period_focus": "Q1",
    "fiscal_year": 2015,
    "doc_type": "10-Q",
    "revenues": 540280000,
    "op_income": 71164000,
    "net_income": 25883000,
    "eps_basic": 0.47,
    "eps_diluted": 0.4,
    "dividend": 0,
    "assets": 2556094000,
    "cur_assets": 678610000,
    "cur_liab": 854210000,
    "cash": 226116000,
    "equity": 303668000,
    "cash_flow_op": 161688000,
    "cash_flow_inv": -13413000,
    "cash_flow_fin": -186246000
  },
  {
    "symbol": "POR",
    "end_date": "2015-03-31",
    "amend": "False",
    "period_focus": "Q1",
    "fiscal_year": 2015,
    "doc_type": "10-Q",
    "revenues": 473000000,
    "op_income": 85000000,
    "net_income": 50000000,
    "eps_basic": 0.64,
    "eps_diluted": 0.62,
    "dividend": 0.28,
    "assets": 7091000000,
    "cur_assets": 584000000,
    "cur_liab": 809000000,
    "cash": 27000000,
    "equity": 1939000000,
    "cash_flow_op": 134000000,
    "cash_flow_inv": -167000000,
    "cash_flow_fin": -67000000
  },
  {
    "symbol": "PPG",
    "end_date": "2015-03-31",
    "amend": "False",
    "period_focus": "Q1",
    "fiscal_year": 2015,
    "doc_type": "10-Q",
    "revenues": 3662000000,
    "op_income": 536000000,
    "net_income": 322000000,
    "eps_basic": 2.36,
    "eps_diluted": 2.34,
    "dividend": 0.33,
    "assets": 17368000000,
    "cur_assets": 7084000000,
    "cur_liab": 4773000000,
    "cash": 735000000,
    "equity": 5158000000,
    "cash_flow_op": -429000000,
    "cash_flow_inv": 35000000,
    "cash_flow_fin": 458000000
  },
  {
    "symbol": "INCR",
    "end_date": "2015-03-31",
    "amend": "False",
    "period_focus": "Q1",
    "fiscal_year": 2015,
    "doc_type": "10-Q",
    "revenues": 308917000,
    "op_income": 32387000,
    "net_income": 25256000,
    "eps_basic": 0.41,
    "eps_diluted": 0.4,
    "dividend": 0,
    "assets": 1276503000,
    "cur_assets": 477322000,
    "cur_liab": 398050000,
    "cash": 156349000,
    "equity": 408954000,
    "cash_flow_op": 43631000,
    "cash_flow_inv": -4870000,
    "cash_flow_fin": -1262000
  },
  {
    "symbol": "INTC",
    "end_date": "2015-03-28",
    "amend": "False",
    "period_focus": "Q1",
    "fiscal_year": 2015,
    "doc_type": "10-Q",
    "revenues": 12781000000,
    "op_income": 2615000000,
    "net_income": 1992000000,
    "eps_basic": 0.42,
    "eps_diluted": 0.41,
    "dividend": 0.48,
    "assets": 89566000000,
    "cur_assets": 26466000000,
    "cur_liab": 15035000000,
    "cash": 4244000000,
    "equity": 54924000000,
    "cash_flow_op": 4415000000,
    "cash_flow_inv": -449000000,
    "cash_flow_fin": -2274000000
  },
  {
    "symbol": "RSG",
    "end_date": "2015-03-31",
    "amend": "False",
    "period_focus": "Q1",
    "fiscal_year": 2015,
    "doc_type": "10-Q",
    "revenues": 2169400000,
    "op_income": 372800000,
    "net_income": 172400000,
    "eps_basic": 0.49,
    "eps_diluted": 0.49,
    "dividend": 0.28,
    "assets": 20593700000,
    "cur_assets": 1343700000,
    "cur_liab": 1756400000,
    "cash": 134300000,
    "equity": 7764700000,
    "cash_flow_op": 496100000,
    "cash_flow_inv": -773400000,
    "cash_flow_fin": 336400000
  },
  {
    "symbol": "INGN",
    "end_date": "2014-12-31",
    "amend": "False",
    "period_focus": "FY",
    "fiscal_year": 2014,
    "doc_type": "10-K",
    "revenues": 73096000,
    "op_income": 10511000,
    "net_income": 6826000,
    "eps_basic": 0.33,
    "eps_diluted": 0.3,
    "dividend": 0,
    "assets": 140085000,
    "cur_assets": 92543000,
    "cur_liab": 18735000,
    "cash": 56836000,
    "equity": 118150000,
    "cash_flow_op": 15697000,
    "cash_flow_inv": -16254000,
    "cash_flow_fin": 43872000
  },
  {
    "symbol": "RLI",
    "end_date": "2015-03-31",
    "amend": "False",
    "period_focus": "Q1",
    "fiscal_year": 2015,
    "doc_type": "10-Q",
    "revenues": 195784000,
    "op_income": "",
    "net_income": 30598000,
    "eps_basic": 0.71,
    "eps_diluted": 0.7,
    "dividend": 0.18,
    "assets": 2780564000,
    "cur_assets": "",
    "cur_liab": "",
    "cash": 31514000,
    "equity": 861995000,
    "cash_flow_op": 23407000,
    "cash_flow_inv": -16443000,
    "cash_flow_fin": -6070000
  },
  {
    "symbol": "SFE",
    "end_date": "2015-03-31",
    "amend": "False",
    "period_focus": "Q1",
    "fiscal_year": 2015,
    "doc_type": "10-Q",
    "revenues": "",
    "op_income": -4880000,
    "net_income": -14603000,
    "eps_basic": -0.7,
    "eps_diluted": -0.7,
    "dividend": 0,
    "assets": 303438000,
    "cur_assets": 111282000,
    "cur_liab": 4970000,
    "cash": 85086000,
    "equity": 244060000,
    "cash_flow_op": -6481000,
    "cash_flow_inv": -20879000,
    "cash_flow_fin": 549000
  },
  {
    "symbol": "JJSF",
    "end_date": "2015-03-28",
    "amend": "False",
    "period_focus": "Q2",
    "fiscal_year": 2015,
    "doc_type": "10-Q",
    "revenues": 225008000,
    "op_income": 21805000,
    "net_income": 14637000,
    "eps_basic": 0.78,
    "eps_diluted": 0.78,
    "dividend": 0,
    "assets": 709313000,
    "cur_assets": 281308000,
    "cur_liab": 90171000,
    "cash": 88615000,
    "equity": 571856000,
    "cash_flow_op": 31228000,
    "cash_flow_inv": -19372000,
    "cash_flow_fin": -12845000
  },
  {
    "symbol": "JBHT",
    "end_date": "2015-03-31",
    "amend": "False",
    "period_focus": "Q1",
    "fiscal_year": 2015,
    "doc_type": "10-Q",
    "revenues": 1440180000,
    "op_income": 155220000,
    "net_income": 91932000,
    "eps_basic": 0.79,
    "eps_diluted": 0.78,
    "dividend": 0.21,
    "assets": 3428997000,
    "cur_assets": 803512000,
    "cur_liab": 762331000,
    "cash": 5646000,
    "equity": 1277380000,
    "cash_flow_op": 255543000,
    "cash_flow_inv": -161344000,
    "cash_flow_fin": -94513000
  },
  {
    "symbol": "KLAC",
    "end_date": "2015-03-31",
    "amend": "False",
    "period_focus": "Q3",
    "fiscal_year": 2015,
    "doc_type": "10-Q",
    "revenues": 738459000,
    "op_income": 194986000,
    "net_income": 131638000,
    "eps_basic": 0.81,
    "eps_diluted": 0.81,
    "dividend": 0.5,
    "assets": 4902220000,
    "cur_assets": 3967111000,
    "cur_liab": 976615000,
    "cash": 621892000,
    "equity": 493941000,
    "cash_flow_op": 288427000,
    "cash_flow_inv": 760380000,
    "cash_flow_fin": -1043294000
  },
  {
    "symbol": "LECO",
    "end_date": "2015-03-31",
    "amend": "False",
    "period_focus": "Q1",
    "fiscal_year": 2015,
    "doc_type": "10-Q",
    "revenues": 657900000,
    "op_income": 90499000,
    "net_income": 68354000,
    "eps_basic": 0.9,
    "eps_diluted": 0.89,
    "dividend": 0.29,
    "assets": 1921508000,
    "cur_assets": 1095002000,
    "cur_liab": 608425000,
    "cash": 289017000,
    "equity": 1179955000,
    "cash_flow_op": 52784000,
    "cash_flow_inv": -9245000,
    "cash_flow_fin": -21422000
  },
  {
    "symbol": "MKTX",
    "end_date": "2015-03-31",
    "amend": "False",
    "period_focus": "Q1",
    "fiscal_year": 2015,
    "doc_type": "10-Q",
    "revenues": 76771000,
    "op_income": "",
    "net_income": 24593000,
    "eps_basic": 0.67,
    "eps_diluted": 0.65,
    "dividend": 0.2,
    "assets": 378694000,
    "cur_assets": "",
    "cur_liab": "",
    "cash": 161048000,
    "equity": 344670000,
    "cash_flow_op": 10034000,
    "cash_flow_inv": -1048000,
    "cash_flow_fin": -17241000
  },
  {
    "symbol": "MXIM",
    "end_date": "2015-03-28",
    "amend": "False",
    "period_focus": "Q3",
    "fiscal_year": 2015,
    "doc_type": "10-Q",
    "revenues": 577263000,
    "op_income": 105450000,
    "net_income": 79433000,
    "eps_basic": 0.28,
    "eps_diluted": 0.28,
    "dividend": 0.28,
    "assets": 4167717000,
    "cur_assets": 2180688000,
    "cur_liab": 355334000,
    "cash": 1392197000,
    "equity": 2253849000,
    "cash_flow_op": 471916000,
    "cash_flow_inv": -59004000,
    "cash_flow_fin": -343187000
  },
  {
    "symbol": "TMUS",
    "end_date": "2015-03-31",
    "amend": "False",
    "period_focus": "Q1",
    "fiscal_year": 2015,
    "doc_type": "10-Q",
    "revenues": 7778000000,
    "op_income": 117000000,
    "net_income": -77000000,
    "eps_basic": -0.09,
    "eps_diluted": -0.09,
    "dividend": 0,
    "assets": 56558000000,
    "cur_assets": 11635000000,
    "cur_liab": 8649000000,
    "cash": 3032000000,
    "equity": 15650000000,
    "cash_flow_op": 489000000,
    "cash_flow_inv": -2692000000,
    "cash_flow_fin": -80000000
  },
  {
    "symbol": "TRN",
    "end_date": "2015-03-31",
    "amend": "False",
    "period_focus": "Q1",
    "fiscal_year": 2015,
    "doc_type": "10-Q",
    "revenues": 1626700000,
    "op_income": 333100000,
    "net_income": 174500000,
    "eps_basic": 1.15,
    "eps_diluted": 1.13,
    "dividend": 0.1,
    "assets": 8722400000,
    "cur_assets": "",
    "cur_liab": "",
    "cash": 590700000,
    "equity": 3551400000,
    "cash_flow_op": 109400000,
    "cash_flow_inv": -323100000,
    "cash_flow_fin": -83500000
  },
  {
    "symbol": "TYC",
    "end_date": "2015-03-27",
    "amend": "False",
    "period_focus": "Q2",
    "fiscal_year": 2015,
    "doc_type": "10-Q",
    "revenues": 2430000000,
    "op_income": 221000000,
    "net_income": 167000000,
    "eps_basic": 0.4,
    "eps_diluted": 0.39,
    "dividend": 0,
    "assets": 11695000000,
    "cur_assets": 4078000000,
    "cur_liab": 3479000000,
    "cash": 432000000,
    "equity": 4230000000,
    "cash_flow_op": 262000000,
    "cash_flow_inv": -703000000,
    "cash_flow_fin": -3000000
  },
  {
    "symbol": "UTX",
    "end_date": "2015-03-31",
    "amend": "False",
    "period_focus": "Q1",
    "fiscal_year": 2015,
    "doc_type": "10-Q",
    "revenues": 14541000000,
    "op_income": 2274000000,
    "net_income": 1426000000,
    "eps_basic": 1.6,
    "eps_diluted": 1.58,
    "dividend": 0,
    "assets": 91327000000,
    "cur_assets": 29958000000,
    "cur_liab": 25729000000,
    "cash": 5281000000,
    "equity": 30167000000,
    "cash_flow_op": 1310000000,
    "cash_flow_inv": 173000000,
    "cash_flow_fin": -1384000000
  },
  {
    "symbol": "NURO",
    "end_date": "2015-03-31",
    "amend": "False",
    "period_focus": "Q1",
    "fiscal_year": 2015,
    "doc_type": "10-Q",
    "revenues": 1282960,
    "op_income": -3258619,
    "net_income": -2071228,
    "eps_basic": -0.25,
    "eps_diluted": -0.25,
    "dividend": 0,
    "assets": 9130902,
    "cur_assets": 8222818,
    "cur_liab": 3318933,
    "cash": 6403123,
    "equity": 1681643,
    "cash_flow_op": -2643681,
    "cash_flow_inv": -175181,
    "cash_flow_fin": ""
  },
  {
    "symbol": "VTR",
    "end_date": "2015-03-31",
    "amend": "False",
    "period_focus": "Q1",
    "fiscal_year": 2015,
    "doc_type": "10-Q",
    "revenues": 884024000,
    "op_income": "",
    "net_income": 120442000,
    "eps_basic": 0.37,
    "eps_diluted": 0.37,
    "dividend": 0.79,
    "assets": 24439871000,
    "cur_assets": "",
    "cur_liab": "",
    "cash": 120225000,
    "equity": 11112964000,
    "cash_flow_op": 344169000,
    "cash_flow_inv": -908530000,
    "cash_flow_fin": 629545000
  },
  {
    "symbol": "WNC",
    "end_date": "2015-03-31",
    "amend": "False",
    "period_focus": "Q1",
    "fiscal_year": 2015,
    "doc_type": "10-Q",
    "revenues": 437597000,
    "op_income": 27263000,
    "net_income": 10474000,
    "eps_basic": 0.15,
    "eps_diluted": 0.15,
    "dividend": 0,
    "assets": 984972000,
    "cur_assets": 547927000,
    "cur_liab": 246356000,
    "cash": 125609000,
    "equity": 384214000,
    "cash_flow_op": 4229000,
    "cash_flow_inv": -2975000,
    "cash_flow_fin": -21758000
  },
  {
    "symbol": "WCN",
    "end_date": "2015-03-31",
    "amend": "False",
    "period_focus": "Q1",
    "fiscal_year": 2015,
    "doc_type": "10-Q",
    "revenues": 506100000,
    "op_income": 101865000,
    "net_income": 51824000,
    "eps_basic": 0.42,
    "eps_diluted": 0.42,
    "dividend": 0.13,
    "assets": 5279574000,
    "cur_assets": 336475000,
    "cur_liab": 357108000,
    "cash": 15734000,
    "equity": 2248583000,
    "cash_flow_op": 162571000,
    "cash_flow_inv": -132174000,
    "cash_flow_fin": -29016000
  },
  {
    "symbol": "WFT",
    "end_date": "2015-03-31",
    "amend": "False",
    "period_focus": "Q1",
    "fiscal_year": 2015,
    "doc_type": "10-Q",
    "revenues": 2794000000,
    "op_income": 50000000,
    "net_income": -118000000,
    "eps_basic": -0.15,
    "eps_diluted": -0.15,
    "dividend": 0,
    "assets": 18223000000,
    "cur_assets": 7592000000,
    "cur_liab": 4393000000,
    "cash": 512000000,
    "equity": 6598000000,
    "cash_flow_op": -42000000,
    "cash_flow_inv": -221000000,
    "cash_flow_fin": 307000000
  },
  {
    "symbol": "PDVW",
    "end_date": "2014-12-31",
    "amend": "True",
    "period_focus": "Q3",
    "fiscal_year": 2015,
    "doc_type": "10-Q",
    "revenues": 835623,
    "op_income": -3530791,
    "net_income": -3525864,
    "eps_basic": -0.28,
    "eps_diluted": -0.28,
    "dividend": 0,
    "assets": 226092512,
    "cur_assets": 123817515,
    "cur_liab": 3398381,
    "cash": 122729111,
    "equity": 216117909,
    "cash_flow_op": 3803589,
    "cash_flow_inv": -91953764,
    "cash_flow_fin": 210833607
  },
  {
    "symbol": "PTEN",
    "end_date": "2015-03-31",
    "amend": "False",
    "period_focus": "Q1",
    "fiscal_year": 2015,
    "doc_type": "10-Q",
    "revenues": 657699000,
    "op_income": 24103000,
    "net_income": 9039000,
    "eps_basic": 0.06,
    "eps_diluted": 0.06,
    "dividend": 0.1,
    "assets": 5230907000,
    "cur_assets": 687620000,
    "cur_liab": 560616000,
    "cash": 86917000,
    "equity": 2898538000,
    "cash_flow_op": 404985000,
    "cash_flow_inv": -235639000,
    "cash_flow_fin": -122080000
  },
  {
    "symbol": "YUM",
    "end_date": "2015-03-21",
    "amend": "False",
    "period_focus": "Q1",
    "fiscal_year": 2015,
    "doc_type": "10-Q",
    "revenues": 2622000000,
    "op_income": 506000000,
    "net_income": 362000000,
    "eps_basic": 0.83,
    "eps_diluted": 0.81,
    "dividend": 0,
    "assets": 8305000000,
    "cur_assets": 1783000000,
    "cur_liab": 2290000000,
    "cash": 675000000,
    "equity": 1763000000,
    "cash_flow_op": 516000000,
    "cash_flow_inv": -196000000,
    "cash_flow_fin": -246000000
  },
  {
    "symbol": "QDEL",
    "end_date": "2015-03-31",
    "amend": "False",
    "period_focus": "Q1",
    "fiscal_year": 2015,
    "doc_type": "10-Q",
    "revenues": 7400000,
    "op_income": 8689000,
    "net_income": 3991000,
    "eps_basic": 0.12,
    "eps_diluted": 0.11,
    "dividend": 0,
    "assets": 455193000,
    "cur_assets": 285291000,
    "cur_liab": 36122000,
    "cash": 229429000,
    "equity": 251451000,
    "cash_flow_op": 31766000,
    "cash_flow_inv": -2867000,
    "cash_flow_fin": -356000
  },
  {
    "symbol": "RMBS",
    "end_date": "2015-03-31",
    "amend": "False",
    "period_focus": "Q1",
    "fiscal_year": 2015,
    "doc_type": "10-Q",
    "revenues": 72914000,
    "op_income": 17892000,
    "net_income": 9502000,
    "eps_basic": 0.08,
    "eps_diluted": 0.08,
    "dividend": 0,
    "assets": 599871000,
    "cur_assets": 335566000,
    "cur_liab": 28029000,
    "cash": 171567000,
    "equity": 405942000,
    "cash_flow_op": 15039000,
    "cash_flow_inv": 1076000,
    "cash_flow_fin": 1326000
  },
  {
    "symbol": "SANM",
    "end_date": "2015-03-28",
    "amend": "False",
    "period_focus": "Q2",
    "fiscal_year": 2015,
    "doc_type": "10-Q",
    "revenues": 1527530000,
    "op_income": 49652000,
    "net_income": 14748000,
    "eps_basic": 0.18,
    "eps_diluted": 0.17,
    "dividend": 0,
    "assets": 3116453000,
    "cur_assets": 2290543000,
    "cur_liab": 1271596000,
    "cash": 407717000,
    "equity": 1276850000,
    "cash_flow_op": 63556000,
    "cash_flow_inv": -44493000,
    "cash_flow_fin": -78837000
  },
  {
    "symbol": "SONS",
    "end_date": "2015-03-27",
    "amend": "False",
    "period_focus": "Q1",
    "fiscal_year": 2015,
    "doc_type": "10-Q",
    "revenues": 50145000,
    "op_income": -18866000,
    "net_income": -19359000,
    "eps_basic": -0.39,
    "eps_diluted": -0.39,
    "dividend": 0,
    "assets": 303994000,
    "cur_assets": 180681000,
    "cur_liab": 68712000,
    "cash": 18092000,
    "equity": 221231000,
    "cash_flow_op": -17476000,
    "cash_flow_inv": -790000,
    "cash_flow_fin": -4744000
  },
  {
    "symbol": "TZOO",
    "end_date": "2015-03-31",
    "amend": "False",
    "period_focus": "Q1",
    "fiscal_year": 2015,
    "doc_type": "10-Q",
    "revenues": 36492000,
    "op_income": 3802000,
    "net_income": 1909000,
    "eps_basic": 0.13,
    "eps_diluted": 0.13,
    "dividend": 0,
    "assets": 89607000,
    "cur_assets": 77444000,
    "cur_liab": 35203000,
    "cash": 53975000,
    "equity": 39602000,
    "cash_flow_op": 2426000,
    "cash_flow_inv": -184000,
    "cash_flow_fin": 0
  },
  {
    "symbol": "UTHR",
    "end_date": "2015-03-31",
    "amend": "False",
    "period_focus": "Q1",
    "fiscal_year": 2015,
    "doc_type": "10-Q",
    "revenues": 327504000,
    "op_income": -14826000,
    "net_income": -16641000,
    "eps_basic": -0.36,
    "eps_diluted": -0.36,
    "dividend": 0,
    "assets": 1894614000,
    "cur_assets": 994091000,
    "cur_liab": 646748000,
    "cash": 426509000,
    "equity": 1091623000,
    "cash_flow_op": 108951000,
    "cash_flow_inv": 68455000,
    "cash_flow_fin": -145477000
  },
  {
    "symbol": "VIRC",
    "end_date": "2015-01-31",
    "amend": "False",
    "period_focus": "FY",
    "fiscal_year": 2014,
    "doc_type": "10-K",
    "revenues": 164052000,
    "op_income": 2372000,
    "net_income": 849000,
    "eps_basic": 0.06,
    "eps_diluted": 0.06,
    "dividend": 0,
    "assets": 81811000,
    "cur_assets": 38971000,
    "cur_liab": 21405000,
    "cash": 470000,
    "equity": 22573000,
    "cash_flow_op": 1659000,
    "cash_flow_inv": -3382000,
    "cash_flow_fin": 1142000
  }
]
